twstatus/__init__.py
twstatus/player.py
twstatus/serverhandler.py
twstatus/serverinfo.py
twstatus.py-0.3.3.dist-info/LICENSE
twstatus.py-0.3.3.dist-info/METADATA
twstatus.py-0.3.3.dist-info/WHEEL
twstatus.py-0.3.3.dist-info/top_level.txt
twstatus.py-0.3.3.dist-info/RECORD
