Metadata-Version: 2.1
Name: twstatus.py
Version: 0.3.3
Summary: Get information about teeworlds/ddnet servers.
Home-page: https://github.com/edg-l/twstatus.py
Author: Edgar
Author-email: git@edgarluque.com
License: MIT
Keywords: teeworlds,servers,info,asyncio
Platform: UNKNOWN
Classifier: Development Status :: 4 - Beta
Classifier: Intended Audience :: Developers
Classifier: Operating System :: OS Independent
Classifier: Topic :: Utilities
Classifier: Topic :: Software Development :: Libraries
Classifier: Topic :: Software Development :: Libraries :: Python Modules
Classifier: License :: OSI Approved :: MIT License
Classifier: Programming Language :: Python :: 3.6
Requires-Python: >=3.6
